{
	"info": {
		"_postman_id": "a1b2c3d4-e5f6-7890-abcd-ef1234567890",
		"name": "Campus Assignment Management API",
		"description": "Postman collection for Campus Assignment Management API with authentication and assignment CRUD operations",
		"schema": "https://schema.getpostman.com/json/collection/v2.1.0/collection.json"
	},
	"item": [
		{
			"name": "Authentication",
			"item": [
				{
					"name": "Register User",
					"request": {
						"method": "POST",
						"header": [
							{
								"key": "Content-Type",
								"value": "application/json"
							}
						],
						"body": {
							"mode": "raw",
							"raw": "{\n    \"name\": \"John Doe\",\n    \"email\": \"john@example.com\",\n    \"password\": \"password123\",\n    \"password_confirmation\": \"password123\",\n    \"department\": \"Computer Science\",\n    \"year\": 3\n}"
						},
						"url": {
							"raw": "{{base_url}}/api/auth/register",
							"host": [
								"{{base_url}}"
							],
							"path": [
								"api",
								"auth",
								"register"
							]
						},
						"description": "Register a new student account"
					},
					"response": []
				},
				{
					"name": "Login",
					"request": {
						"method": "POST",
						"header": [
							{
								"key": "Content-Type",
								"value": "application/json"
							}
						],
						"body": {
							"mode": "raw",
							"raw": "{\n    \"email\": \"john@example.com\",\n    \"password\": \"password123\"\n}"
						},
						"url": {
							"raw": "{{base_url}}/api/auth/login",
							"host": [
								"{{base_url}}"
							],
							"path": [
								"api",
								"auth",
								"login"
							]
						},
						"description": "Login with existing credentials"
					},
					"response": []
				},
				{
					"name": "Get Profile",
					"request": {
						"method": "GET",
						"header": [
							{
								"key": "Authorization",
								"value": "Bearer {{auth_token}}"
							}
						],
						"url": {
							"raw": "{{base_url}}/api/auth/profile",
							"host": [
								"{{base_url}}"
							],
							"path": [
								"api",
								"auth",
								"profile"
							]
						},
						"description": "Get current user profile"
					},
					"response": []
				},
				{
					"name": "Logout",
					"request": {
						"method": "POST",
						"header": [
							{
								"key": "Authorization",
								"value": "Bearer {{auth_token}}"
							}
						],
						"url": {
							"raw": "{{base_url}}/api/auth/logout",
							"host": [
								"{{base_url}}"
							],
							"path": [
								"api",
								"auth",
								"logout"
							]
						},
						"description": "Logout current user"
					},
					"response": []
				}
			],
			"description": "Authentication endpoints for user registration, login, logout, and profile management"
		},
		{
			"name": "Assignments",
			"item": [
				{
					"name": "Get All Assignments",
					"request": {
						"method": "GET",
						"header": [
							{
								"key": "Authorization",
								"value": "Bearer {{auth_token}}"
							}
						],
						"url": {
							"raw": "{{base_url}}/api/assignments",
							"host": [
								"{{base_url}}"
							],
							"path": [
								"api",
								"assignments"
							]
						},
						"description": "Get all assignments for the authenticated user"
					},
					"response": []
				},
				{
					"name": "Create Assignment",
					"request": {
						"method": "POST",
						"header": [
							{
								"key": "Authorization",
								"value": "Bearer {{auth_token}}"
							},
							{
								"key": "Content-Type",
								"value": "application/json"
							}
						],
						"body": {
							"mode": "raw",
							"raw": "{\n    \"title\": \"Database Design Project\",\n    \"description\": \"Create a comprehensive database schema for a library management system\",\n    \"subject\": \"Database Systems\",\n    \"status\": \"Pending\"\n}"
						},
						"url": {
							"raw": "{{base_url}}/api/assignments",
							"host": [
								"{{base_url}}"
							],
							"path": [
								"api",
								"assignments"
							]
						},
						"description": "Create a new assignment"
					},
					"response": []
				},
				{
					"name": "Get Specific Assignment",
					"request": {
						"method": "GET",
						"header": [
							{
								"key": "Authorization",
								"value": "Bearer {{auth_token}}"
							}
						],
						"url": {
							"raw": "{{base_url}}/api/assignments/1",
							"host": [
								"{{base_url}}"
							],
							"path": [
								"api",
								"assignments",
								"1"
							]
						},
						"description": "Get a specific assignment by ID"
					},
					"response": []
				},
				{
					"name": "Update Assignment",
					"request": {
						"method": "PUT",
						"header": [
							{
								"key": "Authorization",
								"value": "Bearer {{auth_token}}"
							},
							{
								"key": "Content-Type",
								"value": "application/json"
							}
						],
						"body": {
							"mode": "raw",
							"raw": "{\n    \"title\": \"Updated Database Design Project\",\n    \"description\": \"Updated description for the database schema project\",\n    \"subject\": \"Advanced Database Systems\",\n    \"status\": \"Submitted\"\n}"
						},
						"url": {
							"raw": "{{base_url}}/api/assignments/1",
							"host": [
								"{{base_url}}"
							],
							"path": [
								"api",
								"assignments",
								"1"
							]
						},
						"description": "Update an existing assignment"
					},
					"response": []
				},
				{
					"name": "Delete Assignment",
					"request": {
						"method": "DELETE",
						"header": [
							{
								"key": "Authorization",
								"value": "Bearer {{auth_token}}"
							}
						],
						"url": {
							"raw": "{{base_url}}/api/assignments/1",
							"host": [
								"{{base_url}}"
							],
							"path": [
								"api",
								"assignments",
								"1"
							]
						},
						"description": "Delete an assignment"
					},
					"response": []
				}
			],
			"description": "Assignment CRUD operations for managing student assignments"
		},
		{
			"name": "System",
			"item": [
				{
					"name": "API Status",
					"request": {
						"method": "GET",
						"header": [],
						"url": {
							"raw": "{{base_url}}/api",
							"host": [
								"{{base_url}}"
							],
							"path": [
								"api"
							]
						},
						"description": "Check API status and information"
					},
					"response": []
				}
			],
			"description": "System information and status endpoints"
		}
	],
	"event": [
		{
			"listen": "prerequest",
			"script": {
				"type": "text/javascript",
				"exec": [
					""
				]
			}
		},
		{
			"listen": "test",
			"script": {
				"type": "text/javascript",
				"exec": [
					""
				]
			}
		}
	],
	"variable": [
		{
			"key": "base_url",
			"value": "http://localhost:8000",
			"type": "string"
		},
		{
			"key": "auth_token",
			"value": "",
			"type": "string"
		}
	]
}
